{
  "$schema": "http://json.schemastore.org/sarif-1.0.0",
  "version": "1.0.0",
  "runs": [
    {
      "tool": {
        "name": "Compilateur Microsoft (R) Visual C#",
        "version": "3.2.0.0",
        "fileVersion": "3.2.1-beta4-19408-03 (2fc6a049)",
        "semanticVersion": "3.2.0",
        "language": "fr-FR"
      },
      "results": [
        {
          "ruleId": "S1118",
          "level": "warning",
          "message": "Add a 'protected' constructor or the 'static' keyword to the class declaration.",
          "locations": [
            {
              "resultFile": {
                "uri": "file:///F:/Documents/GITrepos/Compil/Compil/Compil/Program.cs",
                "region": {
                  "startLine": 11,
                  "startColumn": 11,
                  "endLine": 11,
                  "endColumn": 18
                }
              }
            }
          ],
          "properties": {
            "warningLevel": 1
          }
        },
        {
          "ruleId": "S4823",
          "level": "warning",
          "message": "Make sure that command line arguments are used safely here.",
          "locations": [
            {
              "resultFile": {
                "uri": "file:///F:/Documents/GITrepos/Compil/Compil/Compil/Program.cs",
                "region": {
                  "startLine": 12,
                  "startColumn": 21,
                  "endLine": 12,
                  "endColumn": 25
                }
              }
            }
          ],
          "properties": {
            "warningLevel": 1
          }
        },
        {
          "ruleId": "S3928",
          "level": "warning",
          "message": "The parameter name 'Primary expected.' is not declared in the argument list.",
          "locations": [
            {
              "resultFile": {
                "uri": "file:///F:/Documents/GITrepos/Compil/Compil/Compil/Analyzer/SyntaxAnalyzer.cs",
                "region": {
                  "startLine": 84,
                  "startColumn": 23,
                  "endLine": 84,
                  "endColumn": 69
                }
              }
            }
          ],
          "properties": {
            "warningLevel": 1
          }
        },
        {
          "ruleId": "S1643",
          "level": "warning",
          "message": "Use a StringBuilder instead.",
          "locations": [
            {
              "resultFile": {
                "uri": "file:///F:/Documents/GITrepos/Compil/Compil/Compil/Analyzer/LexicalAnalyzer.cs",
                "region": {
                  "startLine": 122,
                  "startColumn": 21,
                  "endLine": 122,
                  "endColumn": 49
                }
              }
            }
          ],
          "properties": {
            "warningLevel": 1
          }
        },
        {
          "ruleId": "S1643",
          "level": "warning",
          "message": "Use a StringBuilder instead.",
          "locations": [
            {
              "resultFile": {
                "uri": "file:///F:/Documents/GITrepos/Compil/Compil/Compil/Analyzer/LexicalAnalyzer.cs",
                "region": {
                  "startLine": 150,
                  "startColumn": 21,
                  "endLine": 150,
                  "endColumn": 49
                }
              }
            }
          ],
          "properties": {
            "warningLevel": 1
          }
        },
        {
          "ruleId": "S3776",
          "level": "warning",
          "message": "Refactor this method to reduce its Cognitive Complexity from 25 to the 15 allowed.",
          "locations": [
            {
              "resultFile": {
                "uri": "file:///F:/Documents/GITrepos/Compil/Compil/Compil/Analyzer/LexicalAnalyzer.cs",
                "region": {
                  "startLine": 96,
                  "startColumn": 23,
                  "endLine": 96,
                  "endColumn": 33
                }
              }
            }
          ],
          "relatedLocations": [
            {
              "physicalLocation": {
                "uri": "file:///F:/Documents/GITrepos/Compil/Compil/Compil/Analyzer/LexicalAnalyzer.cs",
                "region": {
                  "startLine": 98,
                  "startColumn": 13,
                  "endLine": 98,
                  "endColumn": 15
                }
              }
            },
            {
              "physicalLocation": {
                "uri": "file:///F:/Documents/GITrepos/Compil/Compil/Compil/Analyzer/LexicalAnalyzer.cs",
                "region": {
                  "startLine": 103,
                  "startColumn": 13,
                  "endLine": 103,
                  "endColumn": 18
                }
              }
            },
            {
              "physicalLocation": {
                "uri": "file:///F:/Documents/GITrepos/Compil/Compil/Compil/Analyzer/LexicalAnalyzer.cs",
                "region": {
                  "startLine": 103,
                  "startColumn": 39,
                  "endLine": 103,
                  "endColumn": 41
                }
              }
            },
            {
              "physicalLocation": {
                "uri": "file:///F:/Documents/GITrepos/Compil/Compil/Compil/Analyzer/LexicalAnalyzer.cs",
                "region": {
                  "startLine": 109,
                  "startColumn": 13,
                  "endLine": 109,
                  "endColumn": 15
                }
              }
            },
            {
              "physicalLocation": {
                "uri": "file:///F:/Documents/GITrepos/Compil/Compil/Compil/Analyzer/LexicalAnalyzer.cs",
                "region": {
                  "startLine": 114,
                  "startColumn": 17,
                  "endLine": 114,
                  "endColumn": 19
                }
              }
            },
            {
              "physicalLocation": {
                "uri": "file:///F:/Documents/GITrepos/Compil/Compil/Compil/Analyzer/LexicalAnalyzer.cs",
                "region": {
                  "startLine": 120,
                  "startColumn": 17,
                  "endLine": 120,
                  "endColumn": 22
                }
              }
            },
            {
              "physicalLocation": {
                "uri": "file:///F:/Documents/GITrepos/Compil/Compil/Compil/Analyzer/LexicalAnalyzer.cs",
                "region": {
                  "startLine": 131,
                  "startColumn": 13,
                  "endLine": 131,
                  "endColumn": 15
                }
              }
            },
            {
              "physicalLocation": {
                "uri": "file:///F:/Documents/GITrepos/Compil/Compil/Compil/Analyzer/LexicalAnalyzer.cs",
                "region": {
                  "startLine": 136,
                  "startColumn": 17,
                  "endLine": 136,
                  "endColumn": 19
                }
              }
            },
            {
              "physicalLocation": {
                "uri": "file:///F:/Documents/GITrepos/Compil/Compil/Compil/Analyzer/LexicalAnalyzer.cs",
                "region": {
                  "startLine": 139,
                  "startColumn": 21,
                  "endLine": 139,
                  "endColumn": 23
                }
              }
            },
            {
              "physicalLocation": {
                "uri": "file:///F:/Documents/GITrepos/Compil/Compil/Compil/Analyzer/LexicalAnalyzer.cs",
                "region": {
                  "startLine": 148,
                  "startColumn": 17,
                  "endLine": 148,
                  "endColumn": 22
                }
              }
            },
            {
              "physicalLocation": {
                "uri": "file:///F:/Documents/GITrepos/Compil/Compil/Compil/Analyzer/LexicalAnalyzer.cs",
                "region": {
                  "startLine": 148,
                  "startColumn": 47,
                  "endLine": 148,
                  "endColumn": 49
                }
              }
            },
            {
              "physicalLocation": {
                "uri": "file:///F:/Documents/GITrepos/Compil/Compil/Compil/Analyzer/LexicalAnalyzer.cs",
                "region": {
                  "startLine": 156,
                  "startColumn": 17,
                  "endLine": 156,
                  "endColumn": 19
                }
              }
            },
            {
              "physicalLocation": {
                "uri": "file:///F:/Documents/GITrepos/Compil/Compil/Compil/Analyzer/LexicalAnalyzer.cs",
                "region": {
                  "startLine": 165,
                  "startColumn": 13,
                  "endLine": 165,
                  "endColumn": 15
                }
              }
            },
            {
              "physicalLocation": {
                "uri": "file:///F:/Documents/GITrepos/Compil/Compil/Compil/Analyzer/LexicalAnalyzer.cs",
                "region": {
                  "startLine": 170,
                  "startColumn": 17,
                  "endLine": 170,
                  "endColumn": 19
                }
              }
            },
            {
              "physicalLocation": {
                "uri": "file:///F:/Documents/GITrepos/Compil/Compil/Compil/Analyzer/LexicalAnalyzer.cs",
                "region": {
                  "startLine": 175,
                  "startColumn": 17,
                  "endLine": 175,
                  "endColumn": 19
                }
              }
            },
            {
              "physicalLocation": {
                "uri": "file:///F:/Documents/GITrepos/Compil/Compil/Compil/Analyzer/LexicalAnalyzer.cs",
                "region": {
                  "startLine": 185,
                  "startColumn": 13,
                  "endLine": 185,
                  "endColumn": 19
                }
              }
            }
          ],
          "properties": {
            "warningLevel": 1,
            "customProperties": {
              "0": "+1",
              "1": "+1",
              "10": "+1",
              "11": "+2 (incl 1 for nesting)",
              "12": "+1",
              "13": "+2 (incl 1 for nesting)",
              "14": "+2 (incl 1 for nesting)",
              "15": "+1",
              "2": "+1",
              "3": "+1",
              "4": "+2 (incl 1 for nesting)",
              "5": "+2 (incl 1 for nesting)",
              "6": "+1",
              "7": "+2 (incl 1 for nesting)",
              "8": "+3 (incl 2 for nesting)",
              "9": "+2 (incl 1 for nesting)"
            }
          }
        },
        {
          "ruleId": "S1481",
          "level": "warning",
          "message": "Remove the unused local variable 'buffer'.",
          "locations": [
            {
              "resultFile": {
                "uri": "file:///F:/Documents/GITrepos/Compil/Compil/Compil/Analyzer/LexicalAnalyzer.cs",
                "region": {
                  "startLine": 168,
                  "startColumn": 21,
                  "endLine": 168,
                  "endColumn": 27
                }
              }
            }
          ],
          "properties": {
            "warningLevel": 1
          }
        }
      ],
      "rules": {
        "S1118": {
          "id": "S1118",
          "shortDescription": "Utility classes should not have public constructors",
          "fullDescription": "Utility classes, which are collections of static members, are not meant to be instantiated.",
          "defaultLevel": "warning",
          "helpUri": "https://rules.sonarsource.com/csharp/RSPEC-1118",
          "properties": {
            "category": "Major Code Smell",
            "isEnabledByDefault": true,
            "tags": [
              "C#",
              "SonarWay",
              "MainSourceScope",
              "TestSourceScope"
            ]
          }
        },
        "S1481": {
          "id": "S1481",
          "shortDescription": "Unused local variables should be removed",
          "fullDescription": "If a local variable is declared but not used, it is dead code and should be removed. Doing so will improve maintainability because developers will not wonder what the variable is used for.",
          "defaultLevel": "warning",
          "helpUri": "https://rules.sonarsource.com/csharp/RSPEC-1481",
          "properties": {
            "category": "Minor Code Smell",
            "isEnabledByDefault": true,
            "tags": [
              "C#",
              "SonarWay",
              "MainSourceScope",
              "TestSourceScope"
            ]
          }
        },
        "S1643": {
          "id": "S1643",
          "shortDescription": "Strings should not be concatenated using '+' in a loop",
          "fullDescription": "StringBuilder is more efficient than string concatenation, especially when the operator is repeated over and over as in loops.",
          "defaultLevel": "warning",
          "helpUri": "https://rules.sonarsource.com/csharp/RSPEC-1643",
          "properties": {
            "category": "Minor Code Smell",
            "isEnabledByDefault": true,
            "tags": [
              "C#",
              "SonarWay",
              "MainSourceScope"
            ]
          }
        },
        "S3776": {
          "id": "S3776",
          "shortDescription": "Cognitive Complexity of methods should not be too high",
          "fullDescription": "Cognitive Complexity is a measure of how hard the control flow of a method is to understand. Methods with high Cognitive Complexity will be difficult to maintain.",
          "defaultLevel": "warning",
          "helpUri": "https://rules.sonarsource.com/csharp/RSPEC-3776",
          "properties": {
            "category": "Critical Code Smell",
            "isEnabledByDefault": false,
            "tags": [
              "C#",
              "SonarWay",
              "MainSourceScope",
              "TestSourceScope"
            ]
          }
        },
        "S3928": {
          "id": "S3928",
          "shortDescription": "Parameter names used into ArgumentException constructors should match an existing one ",
          "fullDescription": "Some constructors of the ArgumentException, ArgumentNullException, ArgumentOutOfRangeException and DuplicateWaitObjectException classes must be fed with a valid parameter name. This rule raises an issue in two cases:",
          "defaultLevel": "warning",
          "helpUri": "https://rules.sonarsource.com/csharp/RSPEC-3928",
          "properties": {
            "category": "Major Code Smell",
            "isEnabledByDefault": true,
            "tags": [
              "C#",
              "SonarWay",
              "MainSourceScope",
              "TestSourceScope"
            ]
          }
        },
        "S4823": {
          "id": "S4823",
          "shortDescription": "Using command line arguments is security-sensitive",
          "fullDescription": "Using command line arguments is security-sensitive. It has led in the past to the following vulnerabilities:",
          "defaultLevel": "warning",
          "helpUri": "https://rules.sonarsource.com/csharp/RSPEC-4823",
          "properties": {
            "category": "Critical Security Hotspot",
            "isEnabledByDefault": true,
            "tags": [
              "C#",
              "SonarWay",
              "MainSourceScope",
              "NotConfigurable"
            ]
          }
        }
      }
    }
  ]
}